<?xml version="1.0" encoding="utf-8"?>
<executable>
  <category>Converters</category>
  <title>Nrrd DWI comparison</title>
  <description><![CDATA[Compares two nrrd format DWI images and verifies that gradient magnitudes, gradient directions, measurement frame, and max B0 value are identicle.  Used for testing DicomToNrrdConverter.]]></description>
  <version>0.1.0.$Revision: 916 $(alpha)</version>
  <documentation-url>http://www.slicer.org/slicerWiki/index.php/Documentation/4.1/Modules/DicomToNrrdConverter</documentation-url>
  <license>https://www.nitrc.org/svn/brains/BuildScripts/trunk/License.txt</license>
  <contributor>Mark Scully (UIowa)</contributor>
  <acknowledgements><![CDATA[This work is part of the National Alliance for Medical Image Computing (NAMIC), funded by the National Institutes of Health through the NIH Roadmap for Medical Research, Grant U54 EB005149.  Additional support for DTI data produced on Philips scanners was contributed by Vincent Magnotta and Hans Johnson at the University of Iowa.]]></acknowledgements>
  <parameters>
    <label>IO</label>
    <description><![CDATA[Input/output parameters]]></description>
    <image>
      <name>inputVolume1</name>
      <longflag>--inputVolume1</longflag>
      <label>First input volume</label>
      <channel>input</channel>
      <description><![CDATA[First input volume (.nhdr or .nrrd)]]></description>
    </image>
    <image>
      <name>inputVolume2</name>
      <longflag>--inputVolume2</longflag>
      <label>Second input volume</label>
      <channel>input</channel>
      <description><![CDATA[Second input volume (.nhdr or .nrrd)]]></description>
    </image>
  </parameters>
</executable>
